osa_distributions/Binomialdistribution_challenge.py
osa_distributions/Gaussiandistribution.py
osa_distributions/Generaldistribution.py
osa_distributions/__init__.py
osa_distributions-1.1.dist-info/DESCRIPTION.rst
osa_distributions-1.1.dist-info/METADATA
osa_distributions-1.1.dist-info/RECORD
osa_distributions-1.1.dist-info/WHEEL
osa_distributions-1.1.dist-info/metadata.json
osa_distributions-1.1.dist-info/top_level.txt
