Metadata-Version: 2.0
Name: osa-distributions
Version: 1.1
Summary: Gaussian and Binomial distributions
Home-page: UNKNOWN
Author: Osakpolor Tolulope Obaseki
Author-email: obasekiosa@gmail.com
License: UNKNOWN
Platform: UNKNOWN
